updates2mqtt/__init__.py
updates2mqtt/__main__.py
updates2mqtt/app.py
updates2mqtt/config.py
updates2mqtt/hass_formatter.py
updates2mqtt/model.py
updates2mqtt/mqtt.py
updates2mqtt/py.typed
updates2mqtt/integrations/__init__.py
updates2mqtt/integrations/docker.py
updates2mqtt/integrations/git_utils.py
updates2mqtt-1.5.1.dist-info/METADATA
updates2mqtt-1.5.1.dist-info/WHEEL
updates2mqtt-1.5.1.dist-info/entry_points.txt
updates2mqtt-1.5.1.dist-info/licenses/LICENSE
updates2mqtt-1.5.1.dist-info/RECORD
