Metadata-Version: 2.4
Name: updates2mqtt
Version: 1.5.1
Summary: System update and docker image notification and execution over MQTT
Project-URL: Homepage, https://updates2mqtt.rhizomatics.org.uk
Project-URL: Repository, https://github.com/rhizomatics/updates2mqtt
Project-URL: Documentation, https://updates2mqtt.rhizomatics.org.uk
Project-URL: Issues, https://github.com/rhizomatics/updates2mqtt/issues
Project-URL: Changelog, https://github.com/rhizomatics/updates2mqtt/blob/main/CHANGELOG.md
Author-email: jey burrows <jrb@rhizomatics.org.uk>
License-Expression: Apache-2.0
License-File: LICENSE
Keywords: automation,docker,home-assistant,homeassistant,mqtt,selfhosting,updates
Classifier: Development Status :: 5 - Production/Stable
Classifier: Environment :: Console
Classifier: Intended Audience :: System Administrators
Classifier: License :: OSI Approved :: Apache Software License
Classifier: License :: Other/Proprietary License
Classifier: Natural Language :: English
Classifier: Operating System :: OS Independent
Classifier: Programming Language :: Python
Classifier: Programming Language :: Python :: 3.13
Classifier: Topic :: Home Automation
Classifier: Topic :: System :: Monitoring
Classifier: Topic :: System :: Systems Administration
Classifier: Typing :: Typed
Requires-Python: >=3.13
Requires-Dist: docker>=7.1.0
Requires-Dist: hishel[httpx]>=0.1.4
Requires-Dist: httpx>=0.28.1
Requires-Dist: omegaconf>=2.3.0
Requires-Dist: paho-mqtt>=2.1.0
Requires-Dist: rich>=14.0.0
Requires-Dist: structlog>=25.4.0
Requires-Dist: usingversion>=0.1.2
